pluslife/__init__.py
pluslife/enums.py
pluslife/models.py
pluslife/plot.py
pluslife-1.0.dist-info/METADATA
pluslife-1.0.dist-info/WHEEL
pluslife-1.0.dist-info/top_level.txt
pluslife-1.0.dist-info/RECORD
