Metadata-Version: 2.4
Name: pluslife
Version: 1.0
Summary: Base Data Model for Pluslife to share between projects
Requires-Python: >=3.7
Requires-Dist: matplotlib
Requires-Dist: pillow
Requires-Dist: numpy
Requires-Dist: scipy
